{
  "dbsyncconfig" : {
    "host"     : "localhost",
    "dbname"   : "cexplorer",
    "user"     : "postgres",
    "password" : "MTnk8lsuMM41RgAh1y2WTAUdObsb",
    "port"     : 5432
  },
  "fakedbsyncconfig" : {
      "host"     : "localhost",
      "dbname"   : "govtool",
      "user"     : "postgres",
      "password" : "MTnk8lsuMM41RgAh1y2WTAUdObsb",
      "port"     : 5432
  },
  "port" : 8080,
  "host" : "localhost",
  "cachedurationseconds": 20,
  "sentrydsn": "",
  "sentryenv": "",
  "metadatavalidationhost": "http://metadata-validation",
  "metadatavalidationport": "3000",
  "metadatavalidationmaxconcurrentrequests": 10,
  "redisconfig" : {
      "host"    : "http://redis",
      "port"    : 8094,
      "password": ""
  }
}
